{
    "asin": "B004LXRYTM",
    "title": "Roylco R15286 Antique Paper, 8-3/4 x 11\" Size",
    "brand": "Roylco",
    "feature": [
        "This craft paper is designed to look old and from medieval times",
        "Perfect for giving your project extra authenticity",
        "Antique look really helps to illustrate poems and short stories",
        "Excellent resource for wedding invitations, scrapbooking and more"
    ],
    "description": "Roylco Antique Paper measuring 8-1/2\" x 11\" can be used to draw out an antiqued family tree, family coat of arm or a realistic treasure map. Antique parchment style craft paper helps to illustrate poems and short stories using medieval letter-sets and scripts.",
    "price": null,
    "listPrice": null,
    "prime": true,
    "dimensions": {
        "weight": 31.25,
        "length": 1420.0,
        "width": 919.9999999999999,
        "height": 30.0
    },
    "images": [
        "https://images-na.ssl-images-amazon.com/images/I/41s45%2BKhlvL._SS40_.jpg"
    ],
    "attributes": [
        {
            "name": "Size:",
            "value": "32 Sheets"
        }
    ],
    "categories": [
        {
            "node": "2617941011",
            "title": "Arts, Crafts & Sewing"
        },
        {
            "node": "378733011",
            "title": "Crafting"
        },
        {
            "node": "12897981",
            "title": "Paper & Paper Crafts"
        },
        {
            "node": "12898111",
            "title": "Paper"
        },
        {
            "node": "12898151",
            "title": "Decorative Paper"
        }
    ],
    "similar": [
        "B07CYNZZP5",
        "B07FCTJGHM",
        "B07GRR6FDV",
        "B0011N832C",
        "B06Y26H7VL",
        "B07GH5GS1M",
        "B00ND5A6ZS",
        "B01L2OMUHS",
        "B079SLMRR8",
        "B07GH2RGRG",
        "B001CICTZS",
        "B01N7VQBGG",
        "B071QZH44K",
        "B01IEKQGAU",
        "B06X9D1HSL",
        "B077F6XV1K",
        "B00HE0ZZ22",
        "B01LQ66X84",
        "B006C1NRDI",
        "B07GH4KP5J",
        "B002M7TOXI",
        "B07GH7PVQY",
        "B077BCRRMV",
        "B00L5I3KMG",
        "B07DZGBHLQ",
        "B07GH6BM11",
        "B01BRKG9J2",
        "B01N1ZQEAN",
        "B01EV0YQ7M"
    ],
    "rating": "3.6"
}