{
    "asin": "B008AZV7GI",
    "title": "SunSun JUP-23 13W UV Sterilizer Submersible Pump",
    "brand": "Tech'n'Toy",
    "feature": [
        "Suitable for tanks up to 75-gallons",
        "Dimension: 12.5\" L X 2.75\" W X 2.75\" H",
        "Flow rate: 210 gallon per hour",
        "13 Watt UV light",
        "Submariner UV Sterilizer/Clarifier helps neutralize harmful microorganisms & free-floating algae",
        "Preassembled aquarium UV sterilizer requires no additional pump or plumbing",
        "Suitable for both freshwater, saltwater and pond use",
        "Controllable flow rate"
    ],
    "description": "This amazing SunSun JUP-23 submersible UV sterilizer allows simple and effective UV control of harmful microorganisms & free-floating algae. Compact and versatile units are ready to install - no additional tubing or circulation pump required! Built-in pump directs waterborne organisms past the UV-C lamp for clean, clear aquarium water. Install in vertical or horizontal position right in your aquarium or sump. For fresh, saltwater aquariums or garden ponds. Includes UV unit with built-in pump and UV ballast, UV-C lamp, and suction cup mounting brackets.",
    "price": 3992.0,
    "listPrice": null,
    "prime": true,
    "dimensions": {
        "weight": 260.0,
        "length": 300.0,
        "width": 300.0,
        "height": 1400.0
    },
    "images": [
        "https://images-na.ssl-images-amazon.com/images/I/41v6wY6aqXL._SS40_.jpg",
        "https://images-na.ssl-images-amazon.com/images/I/314Tq57yxaL._SS40_.jpg"
    ],
    "attributes": null,
    "categories": [
        {
            "node": "2619533011",
            "title": "Pet Supplies"
        },
        {
            "node": "2975446011",
            "title": "Fish & Aquatic Pets"
        },
        {
            "node": "2975469011",
            "title": "Aquarium Pumps & Filters"
        },
        {
            "node": "2975470011",
            "title": "Air Pump Accessories"
        }
    ],
    "similar": [
        "B00025694O",
        "B00PSFLBFU",
        "B001KP9B2W",
        "B006WC1F0E",
        "B00F1N7WNO",
        "B071FC295D",
        "B0002563MW",
        "B00CMK2X56",
        "B001KN959I",
        "B008ADUVWQ",
        "B01C6PE4G2",
        "B002ZVODP0",
        "B01A0TMS6Y",
        "B01MA0SILS",
        "B01M1NRGNO",
        "B00C2DBFX4",
        "B00KKUT9A2",
        "B00CLQLRJE",
        "B06W9NJJ1D",
        "B008AJHUME",
        "B01MSISWRQ",
        "B00LLLMTCO",
        "B0757M1S4S",
        "B01824RDNC",
        "B0002A5VK2"
    ],
    "rating": "3.7"
}