{
    "asin": "B00AZ1SMC2",
    "title": "Professional Automatic Temperature Compensation Salinity Refractometer for Aquariums, Marine Monitoring, Saltwater Testing.Dual Sacle: 0-100ppt & 1.000-1.070 Specific Gravity",
    "brand": "Magnum Media Salinity 10ATC",
    "feature": null,
    "description": null,
    "price": 2099.0,
    "listPrice": null,
    "prime": true,
    "dimensions": {
        "weight": 35.0,
        "length": 810.0,
        "width": 320.0,
        "height": 170.0
    },
    "images": [
        "https://images-na.ssl-images-amazon.com/images/I/517zhDQDmrL._SX38_SY50_CR,0,0,38,50_.jpg",
        "https://images-na.ssl-images-amazon.com/images/I/41QiSUqZUrL._SX38_SY50_CR,0,0,38,50_.jpg",
        "https://images-na.ssl-images-amazon.com/images/I/41rnJHskXZL._SX38_SY50_CR,0,0,38,50_.jpg",
        "https://images-na.ssl-images-amazon.com/images/I/51xWTlz0fNL._SX38_SY50_CR,0,0,38,50_.jpg",
        "https://images-na.ssl-images-amazon.com/images/I/41n3Yau7BDL._SX38_SY50_CR,0,0,38,50_.jpg",
        "https://images-na.ssl-images-amazon.com/images/I/41XvUppPZ7L._SX38_SY50_CR,0,0,38,50_.jpg",
        "https://images-na.ssl-images-amazon.com/images/I/51xECOYKPxL._SX38_SY50_CR,0,0,38,50_.jpg"
    ],
    "attributes": null,
    "categories": [],
    "similar": [
        "B07CNL3XYV",
        "B0053DSWJA",
        "B079N97V8C",
        "B073Q22CQW",
        "B007MM0YUU",
        "B01FPG89CE",
        "B0791GFF59",
        "B01LWAFVVN",
        "B076WZGMYT",
        "B001EHGDRM",
        "B07BN9RGGK",
        "B003ODDS5E",
        "B07DL2NJYS",
        "B009XTC4CG",
        "B01FNAPGPA",
        "B077YB2DFW",
        "B001JSXBYO",
        "B07DSTF83R",
        "B01L2OX9KA",
        "B06XC6CV9J",
        "B07C97DYSZ",
        "B001EUE808",
        "B018LRO1SU",
        "B001D6Z7QW",
        "B01LZFXT7S"
    ],
    "rating": "4.2"
}