{
    "asin": "B00QESFJ94",
    "title": "3M Littmann Classic III Monitoring Stethoscope, Black Tube, 27 inch, 5620",
    "brand": "3M Littmann",
    "feature": [
        "Monitor and assess a wide range of patients",
        "Detect normal and abnormal sounds and rhythms",
        "Useful in non-critical care environments such as a medical office, general ward, OB/GYN, ambulatory clinic or urgent care",
        "Monitor and assess a wide range of patients",
        "Detect normal and abnormal sounds and rhythms",
        "Useful in non-critical care environments such as a medical office, general ward, OB/GYN, ambulatory clinic or urgent care",
        "5-year warranty",
        "Fun and vibrant; match color and finish to your personality"
    ],
    "description": "Love your stethoscope The compact and sensitive Littmann Classic III stethoscope is the perfect instrument for clinicians who monitor and assess children or adults in non-critical environments. Manufa ...",
    "price": null,
    "listPrice": null,
    "prime": true,
    "dimensions": {
        "weight": 75.0,
        "length": 170.0,
        "width": 660.0,
        "height": 1270.0
    },
    "images": null,
    "attributes": null,
    "categories": [],
    "similar": [
        "B00445UZ0W",
        "B00KU3GSU8",
        "B01ENFON5A",
        "B01LY82P4J",
        "B0058RPK9G",
        "B019IZZKUC",
        "B001CCINO0",
        "B01CS2OFBW",
        "B000F4W1O4",
        "B01LYVI3Y8",
        "B0132ZPXTC",
        "B06WLLD6ZY"
    ],
    "rating": null
}