{
    "asin": "B00S31I2OO",
    "title": "Cocomii Robot Armor iPhone SE/5S/5 Case New [Heavy Duty] Premium Belt Clip Holster Kickstand Shockproof Bumper [Military Defender] Full Body Dual Layer Rugged Cover for Apple iPhone SE/5S/5 (R.White)",
    "brand": "Cocomii",
    "feature": [
        "TIMELESS DESIGN: Unique. Classy. Power. Quality. Luxury. For the ultimate premium look!",
        "TACTICAL GRIP: Slim, dual layer structure features a TPU body and polycarbonate shock absorbing bumper frame",
        "PERFECT FIT: Precise cutouts ensure easy access to all features and raised lips to protect screen and camera",
        "MULTIFUNCTIONAL: Reinforced 360-degree rotating belt clip holster. Convenient kickstand for hands-free viewing experience",
        "FORTIFIED PROTECTION: MIL-STD 810G 516.6 Certified Military-Grade Protection that you can trust"
    ],
    "description": null,
    "price": 999.0,
    "listPrice": null,
    "prime": true,
    "dimensions": {
        "weight": 15.0,
        "length": 600.0,
        "width": 300.0,
        "height": 50.0
    },
    "images": [
        "https://images-na.ssl-images-amazon.com/images/I/51gEZfoxTLL._SX38_SY50_CR,0,0,38,50_.jpg",
        "https://images-na.ssl-images-amazon.com/images/I/51pKL56n6WL._SX38_SY50_CR,0,0,38,50_.jpg",
        "https://images-na.ssl-images-amazon.com/images/I/516Oyqydz%2BL._SX38_SY50_CR,0,0,38,50_.jpg",
        "https://images-na.ssl-images-amazon.com/images/I/61qdw-1rlAL._SX38_SY50_CR,0,0,38,50_.jpg",
        "https://images-na.ssl-images-amazon.com/images/I/51pKL56n6WL._SX38_SY50_CR,0,0,38,50_.jpg",
        "https://images-na.ssl-images-amazon.com/images/I/51BO3P4mMYL._SX38_SY50_CR,0,0,38,50_.jpg",
        "https://images-na.ssl-images-amazon.com/images/I/51JoirHtTZL._SX38_SY50_CR,0,0,38,50_.jpg"
    ],
    "attributes": [
        {
            "name": "Color:",
            "value": "1"
        }
    ],
    "categories": [
        {
            "node": "2335752011",
            "title": "Cell Phones & Accessories"
        },
        {
            "node": "2407755011",
            "title": "Accessories"
        }
    ],
    "similar": [
        "B01NCLIKE5",
        "B01DR11SRW",
        "B01N0BNEIP",
        "B01EY4TCTM",
        "B01N7IA92J",
        "B01F97AXZ0",
        "B01CKCKEMO",
        "B00S31I2P8",
        "B01FXBZ85C",
        "B00YE5C50A",
        "B00QDKX7EW",
        "B01MA60SC0",
        "B00S31I2QW",
        "B077BVXNNK",
        "B017XHGP4C",
        "B01BYOKMEY",
        "B01F97AY4U",
        "B072F4ZCT2",
        "B01F97AXYG",
        "B01N1SEE6N",
        "B075L1M4ZG",
        "B01CV6Z2IU",
        "B01BYOKKXM",
        "B01BYOKMFI",
        "B019H03CY4",
        "B01I08UTCM",
        "B01N8Q3VKO",
        "B01F97AXWI",
        "B00DD62R40",
        "B01BYOKKYQ",
        "B01BYOKKQO",
        "B07F2XKXZK",
        "B01NAJ9QXK",
        "B01N0BNC8N",
        "B01F97AXXW",
        "B06WWQ8SS7",
        "B01BYOKL36",
        "B00BT8L2MW",
        "B019GZSCQ8",
        "B075L2BSTC",
        "B00YE5C4CY",
        "B00S31I2PI",
        "B01BYOKL4A",
        "B00MIPS6GA",
        "B01F97AY5Y",
        "B072V5K4H8"
    ],
    "rating": "3.3"
}