{
    "asin": "B00WWIFBY8",
    "title": "MOSISO PU Leather Case Only Compatible MacBook 12 Inch with Retina Display A1534 (Version 2017/2016/2015), Premium Quality Book Folio Protective Stand Cover Sleeve, Brown",
    "brand": "MOSISO",
    "feature": [
        "The dimension of case is 11.2 x 7.9 x 0.6 inch. ONLY compatible with MacBook 12 Inch with Retina Display A1534 (Version 2017/2016/2015), please kindly check the model number \"A1xxx\" on the back of the MacBook BEFORE your purchase. Make sure it matches the model number in the title \"A1534\".",
        "WARNING: This case is NOT compatible with MacBook Air 11 Inch No CD-ROM (A1370/A1465), MacBook Pro 13 Inch with Retina Display no CD-Rom(A1502 / A1425, Version 2015 / 2014 / 2013 / end 2012), MacBook Air 13 Inch (A1369/A1466), Old MacBook Pro 13 Inch with CD-ROM (A1278), MacBook White 13 Inch (A1342).",
        "Superior durability case cover with shock-absorbing features. All device features are accessible through cut-outs and openings.",
        "Magnetic closure design makes sure your MacBook be secured in place.",
        "Unique protective design allows operating your MacBook freely without removing the case. MOSISO 1 year warranty on every case."
    ],
    "description": null,
    "price": 1599.0,
    "listPrice": null,
    "prime": true,
    "dimensions": {
        "weight": 56.875,
        "length": 1120.0,
        "width": 790.0,
        "height": 60.0
    },
    "images": [
        "https://images-na.ssl-images-amazon.com/images/I/51eB6QASXNL._SS40_.jpg",
        "https://images-na.ssl-images-amazon.com/images/I/41wNZPMuCkL._SS40_.jpg",
        "https://images-na.ssl-images-amazon.com/images/I/51CAasOQ3mL._SS40_.jpg",
        "https://images-na.ssl-images-amazon.com/images/I/51d2tX1xNQL._SS40_.jpg",
        "https://images-na.ssl-images-amazon.com/images/I/41cUUmxW9jL._SS40_.jpg",
        "https://images-na.ssl-images-amazon.com/images/I/41OcX0OSFKL._SS40_.jpg",
        "https://images-na.ssl-images-amazon.com/images/I/41rrfk9M9uL._SS40_.jpg"
    ],
    "attributes": [
        {
            "name": "Color:",
            "value": "1"
        }
    ],
    "categories": [
        {
            "node": "172282",
            "title": "Electronics"
        },
        {
            "node": "541966",
            "title": "Computers & Accessories"
        },
        {
            "node": "3011391011",
            "title": "Laptop Accessories"
        },
        {
            "node": "172470",
            "title": "Bags, Cases & Sleeves"
        },
        {
            "node": "3095279011",
            "title": "Folio Cases"
        }
    ],
    "similar": [
        "B01CTMJUU2",
        "B012B6VZMW",
        "B073YGFKFR",
        "B0119VROKM",
        "B00WBCBK6I",
        "B01M5H4KRD",
        "B00XK41UDY",
        "B07FQF3LXM",
        "B00QXT47OM",
        "B079K6M2QL",
        "B0761WK7JF",
        "B01M1KA6TF",
        "B07CV9D5PC",
        "B00P5GHZAC",
        "B00VMVY0AC",
        "B075T84YQF",
        "B00XVNWOR0",
        "B00WBCBPDQ",
        "B074PJNHNR",
        "B07BT832H1",
        "B079L5XJ7P",
        "B074PJ69VH",
        "B078YT3W5C",
        "B07FQL84J4",
        "B01LRZ8UXK",
        "B01EY70JPA",
        "B075MVLG99",
        "B015Z7XE0A",
        "B00W253QJ8",
        "B00PQA7PHA",
        "B075T7PW8S",
        "B071FZX25F",
        "B07BT6NMLJ",
        "B073YHHMR9",
        "B00ZUEEOHG",
        "B01M0DO5UL",
        "B07BT3N85P",
        "B079L63NH6",
        "B01EY70KYK",
        "B00WWIG2IW"
    ],
    "rating": "4.7"
}