{
    "asin": "B01C75LJBY",
    "title": "iPad 9.7\" (2017) / iPad Pro 9.7 / iPad Air 2 / iPad Air Screen Protector GARUNK Tempered Glass Screen Protector [Crystal Clear] [Scratch Resist] [Bubble Free Install] [Apple Pencil Compatible]",
    "brand": "GARUNK",
    "feature": [
        "Compatible with: Apple the New iPad 9.7 2018 & 2017, iPad Air 1 (5th Gen), iPad Air 2 (6th Gen), iPad Pro 9.7 [A1822 A1823 A1673 A1674 A1675 A1474 A1475 A1476 A1566 A1567]",
        "Feature: 1).Made of premium Nano-coated tempered glass; 2).9H Hardness Anti-Scratch Explosion-proof; 3).Easy Install Automatic adsorption",
        "High Definition Transparency Film that ensures maximum resolution for RETINA Display",
        "Precise laser cut tempered glass made with polished, rounded edges. [For Better User Experience, We design this screen protector WITHOUT A FRONT CAMERA HOLE, please notice about this]",
        "True Touch Sensitivity and antibacterial for an invisible and perfect protection on touch screen\uff08High-definition bright, Incomparable light transmission up to 99%.All the color of the screen shows incisively and vividly without any distortion. Pictures can be restored completely, which protects eyesight, relieves fatigue, absorbs blue light and protect eyes\uff09"
    ],
    "description": null,
    "price": 750.0,
    "listPrice": null,
    "prime": true,
    "dimensions": {
        "weight": 30.0,
        "length": 930.0000000000001,
        "width": 650.0,
        "height": 0.0
    },
    "images": [
        "https://images-na.ssl-images-amazon.com/images/I/51D3MyzoNZL._SS40_.jpg",
        "https://images-na.ssl-images-amazon.com/images/I/4134paTX-kL._SS40_.jpg",
        "https://images-na.ssl-images-amazon.com/images/I/412Drl43U5L._SS40_.jpg",
        "https://images-na.ssl-images-amazon.com/images/I/41pww8kl0%2BL._SS40_.jpg",
        "https://images-na.ssl-images-amazon.com/images/I/41OQL8Mzo-L._SS40_.jpg",
        "https://images-na.ssl-images-amazon.com/images/I/41hcCDrFoAL._SS40_.jpg"
    ],
    "attributes": [
        {
            "name": "Size:",
            "value": "1"
        }
    ],
    "categories": [
        {
            "node": "172282",
            "title": "Electronics"
        },
        {
            "node": "541966",
            "title": "Computers & Accessories"
        },
        {
            "node": "2348628011",
            "title": "Tablet Accessories"
        },
        {
            "node": "2348631011",
            "title": "Screen Protectors"
        }
    ],
    "similar": [
        "B01C84ITBC",
        "B00SF6VSVG",
        "B013JZCAZK",
        "B07FPBP3BY",
        "B07FQTVFMM",
        "B00X28GH0Y",
        "B07C2P9MDP",
        "B072MNR34R",
        "B072FNV7S2",
        "B06XSCDM4X",
        "B07C2W61ZT",
        "B074947X32",
        "B0187AEJTM",
        "B07FY6KQNK",
        "B00RNGOBYK",
        "B0793QFP69",
        "B01D830T4C",
        "B071QY76PD",
        "B06XT31NXQ",
        "B07C56PMMK",
        "B06Y19L37Z",
        "B072X79WSL",
        "B00RVDMTDU",
        "B07D2DFDW1",
        "B07D3N8ZYC",
        "B00G5N0ZZQ"
    ],
    "rating": "4.0"
}