{
    "asin": "B01D95VYKM",
    "title": "Carved Galleon Engraved Cherry iPhone SE Traveler Wood Case - Black Protective Bumper with Real All Wooden Cover",
    "brand": "Carved",
    "feature": null,
    "description": null,
    "price": null,
    "listPrice": null,
    "prime": true,
    "dimensions": {
        "weight": 9.0,
        "length": 490.00000000000006,
        "width": 240.0,
        "height": 40.0
    },
    "images": [
        "https://images-na.ssl-images-amazon.com/images/I/51YOhOw%2BYwL._SR38,50_.jpg",
        "https://images-na.ssl-images-amazon.com/images/I/41CfBFLpuEL._SR38,50_.jpg",
        "https://images-na.ssl-images-amazon.com/images/I/618xETDWscL._SR38,50_.jpg"
    ],
    "attributes": null,
    "categories": [],
    "similar": [
        "B01INXLNSI"
    ],
    "rating": null
}