{
    "asin": "B01ER9624M",
    "title": "ProCIV Gold Roses, 24K Gold Foil Decoration Artificial Rose Flowers in Gift Box, Best Gift for Mother's Day, Valentine's Day, Wedding Day, Birthday, Christmas, Thanksgiving, Home Decor",
    "brand": "ProCIV",
    "feature": [
        "Gold Roses are real roses dipped in 24K gold to preserve the roses for a lifetime. Rose represent love, and 24k gold rose stand for forever love.",
        "Each rose is precisely hand crafted by skilled artisans, 24k gold rose take over 4 days handwork and 65 steps to make one piece. Made By the Highly Purified 24K 99.9% Gold. Unique long lasting luster. Brilliant and elegant. Without greeting cards and logo dust cloth is fake, ProCIV responsible for the quality of the Flowers, please distinguish it from another sales.",
        "Love Will Never Fade in 24K Foil Artificial Gloden Flowers! Roses have always been a symbol of beauty, love and appreciation. This gold foil rose is a pleasant gifts for mom, for wife, for girlfriend. Besides, it is very suitable for home table decoration, office arrangement, party wedding decoration. One exquisite shows your delicate and romantic life style!",
        "Gift Ideas: Woderful Gift for Valentine's Day, Presents for Birthday, Party, Wedding, Mother's Day, Christmas, Thanksgiving, Graduations, Teachers\u2019 Day, Anniversaries, Retirement, Funerals; Creative gifts for female eldership, lovers, children, friends, company staff and so on. Diameter: approx. 8.5cm / 3.3\"; Height: approx. 26cm / 10\".",
        "Please Be Careful, there are some sellers posing as our brand in the sales of poor quality products, such as:\"Jamoefd\u201c \u201dWatfee\",\"Myrice\" For customers to buy poor quality products from Watfee seller, this team is not responsible, careful to buy. ProCIV has a complaint to Amazon team, we will pursue in the end."
    ],
    "description": null,
    "price": null,
    "listPrice": null,
    "prime": true,
    "dimensions": {
        "weight": 48.75,
        "length": 1110.0,
        "width": 470.0,
        "height": 300.0
    },
    "images": [
        "https://images-na.ssl-images-amazon.com/images/I/51D3zYlOUcL._SS40_.jpg",
        "https://images-na.ssl-images-amazon.com/images/I/412BhdanDVL._SS40_.jpg",
        "https://images-na.ssl-images-amazon.com/images/I/51hx5BmbPCL._SS40_.jpg",
        "https://images-na.ssl-images-amazon.com/images/I/416rxtVS-IL._SS40_.jpg",
        "https://images-na.ssl-images-amazon.com/images/I/51gC0n22IfL._SS40_.jpg",
        "https://images-na.ssl-images-amazon.com/images/I/51w6mnrD%2BmL._SS40_.jpg",
        "https://images-na.ssl-images-amazon.com/images/I/616NN6rIh%2BL._SS40_.jpg"
    ],
    "attributes": [
        {
            "name": "Color:",
            "value": "Gold Rose"
        }
    ],
    "categories": [
        {
            "node": "1055398",
            "title": "Home & Kitchen"
        },
        {
            "node": "901590",
            "title": "Event & Party Supplies"
        },
        {
            "node": "723469011",
            "title": "Decorations"
        },
        {
            "node": "8147482011",
            "title": "Banners & Garlands"
        }
    ],
    "similar": [
        "B01FLM27XY",
        "B07BLJBCDK",
        "B01HB55Q7I",
        "B07F38K7JC",
        "B01N43N3N3",
        "B01HB55PZG",
        "B078ZTCB4H",
        "B01BI8GSBC",
        "B07DY53WZB",
        "B01FGNVXOC",
        "B072M72RY6",
        "B07GPCJGQ8",
        "B07232RF63",
        "B0792KP678",
        "B01FLMXRN8",
        "B07G41XP7B",
        "B013B4TH9G",
        "B00TG2BBNS",
        "B07CHB9K69",
        "B01JLG7HAO",
        "B07F854J53",
        "B07BN9D451",
        "B00F35JSSM",
        "B00361WV84",
        "B078PZSWF1",
        "B01MY2LC86",
        "B01DNAC0XS",
        "B01NBDXBOS",
        "B00JVOSPS0",
        "B00JVOZMIQ"
    ],
    "rating": "3.2"
}