{
    "asin": "B01IO3IGSC",
    "title": null,
    "brand": "Daron",
    "feature": [
        "Die-cast metal with plastic base",
        "Highly detailed and accurate art!",
        "Part of the Postage Stamp collection from Daron",
        "Die-cast metal with plastic base",
        "Highly detailed and accurate art!",
        "Part of the Postage Stamp collection from Daron"
    ],
    "description": "The F-86 Sabre is the United States' first swept wing jet-fighter. Produced by North American aviation it was used extensively against the Soviet MiG-15 in high-speed aerial dogfights during the Korea ...",
    "price": null,
    "listPrice": null,
    "prime": true,
    "dimensions": {
        "weight": 20.0,
        "length": 400.0,
        "width": 400.0,
        "height": 400.0
    },
    "images": null,
    "attributes": null,
    "categories": [],
    "similar": [
        "B007KMZLMS",
        "B00TVFZOLU",
        "B01D6OEDE0",
        "B017BDU6TI",
        "B01D6ODFDU",
        "B00SARI62Y",
        "B00TVFZLYU"
    ],
    "rating": null
}