{
    "asin": "B06Y26X9SJ",
    "title": "Barbra's Junior Size Stripe Wireless Light Padded A Cup Bras",
    "brand": "Barbra Lingerie",
    "feature": [
        "90% Cotton, 10% Spandex",
        "Barbra's 5 Pack Junior's Wireless Light Padded A cup Bras with Better Fabric",
        "5 Assorted Color (2 White, 1 Gray, 1 Black and 1 Salmon)",
        "2 Hook and eye closure adjustable to three sizes",
        "Fully adjustable straps and back closure",
        "Ideal for everyday comfort or dressy occasions for firm support. The fit makes any outfit look just right."
    ],
    "description": "Barbra Lingerie offers high quality of 6 Pack Junior's Stripe Wireless Light Padded A cup Bras at affordable price.",
    "price": 2199.0,
    "listPrice": null,
    "prime": true,
    "dimensions": {
        "weight": 93.75,
        "length": null,
        "width": null,
        "height": null
    },
    "images": [
        "https://images-na.ssl-images-amazon.com/images/I/514JtrRnTsL._SR38,50_.jpg",
        "https://images-na.ssl-images-amazon.com/images/I/41-e5d%2B9OfL._SR38,50_.jpg",
        "https://images-na.ssl-images-amazon.com/images/I/51WSPShMtNL._SR38,50_.jpg",
        "https://images-na.ssl-images-amazon.com/images/I/41FxRhV5VAL._SR38,50_.jpg",
        "https://images-na.ssl-images-amazon.com/images/I/416Dd7Px7rL._SR38,50_.jpg",
        "https://images-na.ssl-images-amazon.com/images/I/41g3nRGDiEL._SR38,50_.jpg",
        "https://images-na.ssl-images-amazon.com/images/I/41I40ZQGj9L._SR38,50_.jpg"
    ],
    "attributes": [
        {
            "name": "Size:",
            "value": "30A"
        },
        {
            "name": "Color:",
            "value": "B2body Bras"
        }
    ],
    "categories": [
        {
            "node": "7141123011",
            "title": "Clothing, Shoes & Jewelry"
        },
        {
            "node": "7147440011",
            "title": "Women"
        },
        {
            "node": "1040660",
            "title": "Clothing"
        },
        {
            "node": "9522931011",
            "title": "Lingerie, Sleep & Lounge"
        },
        {
            "node": "14333511",
            "title": "Lingerie"
        },
        {
            "node": "1044960",
            "title": "Bras"
        },
        {
            "node": "2376204011",
            "title": "Everyday Bras"
        }
    ],
    "similar": [
        "B01DL8O828",
        "B079YF1241",
        "B073R6FBW8",
        "B07CWSNWQJ",
        "B07D61GH4L",
        "B01MZ078JP",
        "B07GP4HCW8",
        "B07G37CKCZ",
        "B078KWW7V5",
        "B00LVQKJOE",
        "B0799L48QW",
        "B007HJFMFU",
        "B076BMTRDT",
        "B07C8L8BX2",
        "B073ZPJ5GV",
        "B01IC9Y1BE",
        "B07G8WQS3H",
        "B01K4R71EQ",
        "B00JHEJ48O",
        "B00PZY3F4O",
        "B01K4R7LA0",
        "B0789SSM8S",
        "B01FEB3Y9I",
        "B073R6NH7M",
        "B07G7Z976R",
        "B077YDJX5C",
        "B07H17Q1XQ",
        "B01ICBGB6U",
        "B01K4R6L6U",
        "B07G37V856",
        "B01C93D1L0",
        "B07GJGYY82",
        "B07CYXBJ1J"
    ],
    "rating": "4.3"
}