{
    "asin": "B07B7JR1NH",
    "title": "Long Lasting Lipstick, Shouhengda Waterproof Lipstick Matte Lipstick Makeup 12 Colors High-end Gift Box Packaging Lipstick Set A01",
    "brand": "Shouhengda",
    "feature": null,
    "description": null,
    "price": 2777.0,
    "listPrice": null,
    "prime": true,
    "dimensions": {
        "weight": 140.0,
        "length": null,
        "width": null,
        "height": null
    },
    "images": [
        "https://images-na.ssl-images-amazon.com/images/I/415wcYjBnWL._SS40_.jpg",
        "https://images-na.ssl-images-amazon.com/images/I/51AcZEkyMWL._SS40_.jpg",
        "https://images-na.ssl-images-amazon.com/images/I/51LBSX8txlL._SS40_.jpg",
        "https://images-na.ssl-images-amazon.com/images/I/31P46wY7UzL._SS40_.jpg",
        "https://images-na.ssl-images-amazon.com/images/I/610pa4vBXjL._SS40_.jpg",
        "https://images-na.ssl-images-amazon.com/images/I/51NXc%2BI25pL._SS40_.jpg",
        "https://images-na.ssl-images-amazon.com/images/I/41pvsPG2H0L._SS40_.jpg"
    ],
    "attributes": null,
    "categories": [
        {
            "node": "3760911",
            "title": "Beauty & Personal Care"
        },
        {
            "node": "11058281",
            "title": "Makeup"
        },
        {
            "node": "11059031",
            "title": "Lips"
        },
        {
            "node": "11059111",
            "title": "Lipstick"
        }
    ],
    "similar": [
        "B077GTYNVR",
        "B074XG4KGF",
        "B07CM6NMG8",
        "B075TDYHCL",
        "B000IEMGGE",
        "B0779TB9RL",
        "B00CVDTMI0",
        "B075KLBRJZ",
        "B075FL6RVN",
        "B07CWMNTRX",
        "B077SDB693",
        "B07889QMQH",
        "B075T5Y9JD",
        "B07D35VX4D",
        "B077P2FCFV",
        "B07CJNWG8J",
        "B078K6GTPW",
        "B00PGQYEUK",
        "B06XF1Y8W1",
        "B0047ERRHO",
        "B07FSHH62B",
        "B06XF43M8G",
        "B0762M2ZWJ",
        "B07232VBZ5",
        "B078JDYPYS",
        "B07BLNHQQG",
        "B07C1NXMBL",
        "B00B4YVU4G",
        "B0777KRYCH",
        "B005UKZAJG",
        "B07DHM36GH"
    ],
    "rating": "3.6"
}